<?xml version="1.0"?>
<!DOCTYPE hibernate-mapping PUBLIC "-//Hibernate/Hibernate Mapping DTD 3.0//EN"
"http://www.hibernate.org/dtd/hibernate-mapping-3.0.dtd">
<!-- Generated May 29, 2022 9:16:33 PM by Hibernate Tools 4.3.1 -->
<hibernate-mapping>
    <class name="model.Sinhvien" table="sinhvien" catalog="sinhvien" optimistic-lock="version">
        <id name="ma" type="java.lang.Integer">
            <column name="ma" />
            <generator class="identity" />
        </id>
        <property name="ten" type="string">
            <column name="ten" length="30" not-null="true" />
        </property>
        <property name="phai" type="boolean">
            <column name="phai" not-null="true" />
        </property>
        <property name="lop" type="string">
            <column name="lop" length="10" not-null="true" />
        </property>
        <property name="diem" type="double">
            <column name="diem" precision="22" scale="0" not-null="true" />
        </property>
    </class>
</hibernate-mapping>
